pychord/__init__.py
pychord/analyzer.py
pychord/chord.py
pychord/parser.py
pychord/progression.py
pychord/quality.py
pychord/utils.py
pychord/constants/__init__.py
pychord/constants/qualities.py
pychord/constants/scales.py
pychord-1.2.1.dist-info/LICENSE
pychord-1.2.1.dist-info/METADATA
pychord-1.2.1.dist-info/WHEEL
pychord-1.2.1.dist-info/top_level.txt
pychord-1.2.1.dist-info/zip-safe
pychord-1.2.1.dist-info/RECORD
