Metadata-Version: 2.1
Name: pychord
Version: 1.2.1
Summary: A library to handle musical chords in python.
Home-page: https://github.com/yuma-m/pychord
Author: Yuma Mihira
Author-email: info@yuma.cloud
License: MIT
Keywords: music chord
Classifier: Development Status :: 5 - Production/Stable
Classifier: Environment :: Console
Classifier: Intended Audience :: Developers
Classifier: Natural Language :: English
Classifier: Operating System :: OS Independent
Classifier: Programming Language :: Python :: 3 :: Only
Classifier: Topic :: Multimedia :: Sound/Audio
Classifier: Topic :: Software Development :: Libraries :: Python Modules
Classifier: Topic :: Utilities
Classifier: License :: OSI Approved :: MIT License
Requires-Python: >=3.6
License-File: LICENSE
